rvfont/__init__.py
rvfont/rvfontchooser.py
rvfont-1.0.4.dist-info/LICENSE
rvfont-1.0.4.dist-info/METADATA
rvfont-1.0.4.dist-info/WHEEL
rvfont-1.0.4.dist-info/top_level.txt
rvfont-1.0.4.dist-info/RECORD
