Metadata-Version: 2.1
Name: rvfont
Version: 1.0.4
Summary: It's fontchooser GUI for Python
Home-page: https://github.com/ravikiranb36/rvfont.git
Author: Ravikirana B
Author-email: ravikiranb36@gmail.com
License: MIT
Platform: UNKNOWN
Classifier: Programming Language :: Python :: 3
Classifier: License :: OSI Approved :: MIT License
Classifier: Operating System :: OS Independent
Requires-Python: >=3.5
